qlisp/__init__.py
qlisp/_draw.py
qlisp/_pauli.cpython-310-darwin.so
qlisp/_tensor.cpython-310-darwin.so
qlisp/cache.py
qlisp/math.py
qlisp/matricies.cpython-310-darwin.so
qlisp/matricies.pyi
qlisp/matricies.pyx
qlisp/simple.cpython-310-darwin.so
qlisp/simple.pyi
qlisp/simple.pyx
qlisp/version.py
qlisp/circuits/__init__.py
qlisp/circuits/all_xy.py
qlisp/circuits/dd.py
qlisp/circuits/rb.py
qlisp/circuits/tomo.py
qlisp/circuits/utils.py
qlisp/circuits/xeb.py
qlisp/circuits/_rb/__init__.py
qlisp/circuits/_rb/clifford.py
qlisp/circuits/_rb/seq2mat.py
qlisp/clifford/__init__.py
qlisp/clifford/group.py
qlisp/clifford/group2.py
qlisp/clifford/utils.py
qlisp/linalg/__init__.py
qlisp/linalg/kak_decomposition.py
qlisp/old/__init__.py
qlisp/old/cache.py
qlisp/old/math.py
qlisp/old/rb.py
qlisp/old/tomo.py
qlisp-1.2.3.dist-info/licenses/LICENSE
qlisp-1.2.3.dist-info/METADATA
qlisp-1.2.3.dist-info/WHEEL
qlisp-1.2.3.dist-info/top_level.txt
qlisp-1.2.3.dist-info/RECORD
